cta/__init__.py
cta/admin.py
cta/apps.py
cta/static/css/cta/bethany_ds.css
cta/static/css/cta/medicio_ds.css
cta/static/css/cta/medilab_ds.css
cta/static/css/cta/mentor_ds.css
cta/static/img/cta/bethany_ds.jpg
cta/static/img/cta/bethany_ds3.jpg
cta/templates/cta/_common.html
cta/templates/cta/bethany_ds.html
cta/templates/cta/medicio_ds.html
cta/templates/cta/medilab_ds.html
cta/templates/cta/mentor_ds.html
cta/templatetags/__init__.py
cta/templatetags/cta_tags.py
django_cta_ds-1.1.0.dist-info/LICENSE
django_cta_ds-1.1.0.dist-info/METADATA
django_cta_ds-1.1.0.dist-info/WHEEL
django_cta_ds-1.1.0.dist-info/top_level.txt
django_cta_ds-1.1.0.dist-info/RECORD
